autocleus/__init__.py
autocleus/main.py
autocleus/climaker/__init__.py
autocleus/climaker/builder.py
autocleus/climaker/components.py
autocleus/climaker/experimental.py
autocleus/climaker/pkgspec.py
autocleus/cmd/__init__.py
autocleus/cmd/generate.py
autocleus/forms/concretize_cli.py
autocleus/forms/custom_cli.py
autocleus/hooks/__init__.py
autocleus/hooks/concretize.py
autocleus/hooks/custom_cli.py
autocleus/library/__init__.py
autocleus/library/autocleus
autocleus/library/db_utils.py
autocleus/library/licenses.py
autocleus/library/parsers.py
autocleus/library/styles.py
autocleus/library/venv_utils.py
autocleus/templates/Apache-2.0.lic
autocleus/templates/BSD-3.lic
autocleus/templates/MIT.lic
autocleus/templates/__init__.py
autocleus/templates/main.j2
autocleus/templates/setup.j2
autocleus-0.1.1.data/scripts/autocleus
autocleus-0.1.1.dist-info/LICENSE
autocleus-0.1.1.dist-info/METADATA
autocleus-0.1.1.dist-info/WHEEL
autocleus-0.1.1.dist-info/top_level.txt
autocleus-0.1.1.dist-info/RECORD
