Metadata-Version: 2.1
Name: autocleus
Version: 0.1.1
Summary: A command line interface for creating your own command line interface
Home-page: https://github.com/ludah65/autocleus.git
Author: Christopher Demone
Author-email: c.demone@hotmail.com
License: LICENSE
Platform: UNKNOWN
Requires-Dist: Pydantic (==1.7.3)
Requires-Dist: typing (==3.7.4.3)
Requires-Dist: PyInquirer (==1.0.3)
Requires-Dist: virtualenv (==20.4.4)
Requires-Dist: art (==5.1)
Requires-Dist: jinja2 (==2.10.1)
Requires-Dist: setuptools (==45.2.0)
Requires-Dist: asciimatics (==1.13.0)
Requires-Dist: yaspin (==1.5.0)
Requires-Dist: yamldirs (==1.1.8)
